mocp/__init__.py
mocp/exceptions.py
mocp/bin/mocp-notify.py
mocp/protocol/__init__.py
mocp/protocol/command.py
mocp/protocol/event.py
mocp/protocol/state.py
py_mocp-0.1rc6.data/scripts/mocp-notify.py
py_mocp-0.1rc6.dist-info/LICENSE
py_mocp-0.1rc6.dist-info/METADATA
py_mocp-0.1rc6.dist-info/WHEEL
py_mocp-0.1rc6.dist-info/top_level.txt
py_mocp-0.1rc6.dist-info/RECORD
